huskar_sdk_v2/__init__.py
huskar_sdk_v2/common.py
huskar_sdk_v2/consts.py
huskar_sdk_v2/exceptions.py
huskar_sdk_v2/service_watcher.py
huskar_sdk_v2/six.py
huskar_sdk_v2/bootstrap/__init__.py
huskar_sdk_v2/bootstrap/client.py
huskar_sdk_v2/bootstrap/components/__init__.py
huskar_sdk_v2/bootstrap/components/config.py
huskar_sdk_v2/bootstrap/components/service_consumer.py
huskar_sdk_v2/bootstrap/components/service_registry.py
huskar_sdk_v2/bootstrap/components/switch.py
huskar_sdk_v2/http/__init__.py
huskar_sdk_v2/http/patterns.py
huskar_sdk_v2/http/service_registry.py
huskar_sdk_v2/http/statsd.py
huskar_sdk_v2/http/components/__init__.py
huskar_sdk_v2/http/components/config.py
huskar_sdk_v2/http/components/service.py
huskar_sdk_v2/http/components/switch.py
huskar_sdk_v2/http/ioloops/__init__.py
huskar_sdk_v2/http/ioloops/entity.py
huskar_sdk_v2/http/ioloops/events.py
huskar_sdk_v2/http/ioloops/file.py
huskar_sdk_v2/http/ioloops/http.py
huskar_sdk_v2/utils/__init__.py
huskar_sdk_v2/utils/cached_dict.py
huskar_sdk_v2/utils/filelock.py
huskar_sdk_v2/utils/format.py
huskar_sdk_v2/utils/go.py
huskar_sdk_v2-0.18.0.dist-info/LICENSE
huskar_sdk_v2-0.18.0.dist-info/METADATA
huskar_sdk_v2-0.18.0.dist-info/WHEEL
huskar_sdk_v2-0.18.0.dist-info/top_level.txt
huskar_sdk_v2-0.18.0.dist-info/RECORD
