Metadata-Version: 2.1
Name: huskar-sdk-v2
Version: 0.18.0
Summary: UNKNOWN
Home-page: https://github.com/huskar-org/huskar-python
Author: Haochuan Guo
Author-email: guohaochuan@gmail.com
License: MIT
Keywords: huskar
Platform: UNKNOWN
Requires-Dist: simplejson (==3.7.3)
Requires-Dist: blinker (==1.3)
Requires-Dist: gevent (<1.3.0,>=1.0.1)
Requires-Dist: atomicfile (==1.0)
Requires-Dist: requests
Provides-Extra: bootstrap
Requires-Dist: kazoo ; extra == 'bootstrap'
Provides-Extra: doc
Requires-Dist: Sphinx (==1.3.1) ; extra == 'doc'
Requires-Dist: sphinx-rtd-theme (==0.1.8) ; extra == 'doc'
Provides-Extra: test
Requires-Dist: pytest (==3.2.2) ; extra == 'test'
Requires-Dist: pylint (==1.6.4) ; extra == 'test'
Requires-Dist: pytest-cov (==2.5.1) ; extra == 'test'
Requires-Dist: pytest-xdist (==1.20.0) ; extra == 'test'
Requires-Dist: pytest-mock (==1.6.2) ; extra == 'test'
Requires-Dist: mock (==2.0.0) ; extra == 'test'
